README.md
setup.py
addressparser/__init__.py
addressparser/__main__.py
addressparser/drawer.py
addressparser/exceptions.py
addressparser/pca.csv
addressparser/structures.py
addressparser.egg-info/PKG-INFO
addressparser.egg-info/SOURCES.txt
addressparser.egg-info/dependency_links.txt
addressparser.egg-info/requires.txt
addressparser.egg-info/top_level.txt