Metadata-Version: 2.1
Name: addressparser
Version: 0.2.4
Summary: Chinese Address Parser and Extraction Tool,Chinese Province, City and Area Recognition Utilities
Home-page: https://github.com/shibing624/addressparser
Author: XuMing
Author-email: xuming624@qq.com
License: MIT
Keywords: NLP,Simplified Chinese,Chinese geographic information
Platform: UNKNOWN
Classifier: Intended Audience :: Developers
Classifier: Operating System :: OS Independent
Classifier: Natural Language :: Chinese (Simplified)
Classifier: Natural Language :: Chinese (Traditional)
Classifier: Programming Language :: Python
Classifier: Programming Language :: Python :: 2.7
Classifier: Programming Language :: Python :: 3
Classifier: Topic :: Text Processing
Classifier: Topic :: Text Processing :: Indexing
Classifier: Topic :: Text Processing :: Linguistic
